[
    {
        "url": "https://genshin-impact.fandom.com/wiki/Albedo"
    },
    {
        "url": "https://genshin-impact.fandom.com/wiki/Aloy"
    },
    {
        "url": "https://genshin-impact.fandom.com/wiki/Amber"
    },
    {
        "url": "https://genshin-impact.fandom.com/wiki/Arataki_Itto"
    },
    {
        "url": "https://genshin-impact.fandom.com/wiki/Barbara"
    },
    {
        "url": "https://genshin-impact.fandom.com/wiki/Beidou"
    },
    {
        "url": "https://genshin-impact.fandom.com/wiki/Bennett"
    },
    {
        "url": "https://genshin-impact.fandom.com/wiki/Chongyun"
    },
    {
        "url": "https://genshin-impact.fandom.com/wiki/Diluc"
    },
    {
        "url": "https://genshin-impact.fandom.com/wiki/Diona"
    },
    {
        "url": "https://genshin-impact.fandom.com/wiki/Eula"
    },
    {
        "url": "https://genshin-impact.fandom.com/wiki/Fischl"
    },
    {
        "url": "https://genshin-impact.fandom.com/wiki/Ganyu"
    },
    {
        "url": "https://genshin-impact.fandom.com/wiki/Gorou"
    },
    {
        "url": "https://genshin-impact.fandom.com/wiki/Hu_Tao"
    },
    {
        "url": "https://genshin-impact.fandom.com/wiki/Jean"
    },
    {
        "url": "https://genshin-impact.fandom.com/wiki/Kaedehara_Kazuha"
    },
    {
        "url": "https://genshin-impact.fandom.com/wiki/Kaeya"
    },
    {
        "url": "https://genshin-impact.fandom.com/wiki/Kamisato_Ayaka"
    },
    {
        "url": "https://genshin-impact.fandom.com/wiki/Keqing"
    },
    {
        "url": "https://genshin-impact.fandom.com/wiki/Klee"
    },
    {
        "url": "https://genshin-impact.fandom.com/wiki/Kujou_Sara"
    },
    {
        "url": "https://genshin-impact.fandom.com/wiki/Lisa"
    },
    {
        "url": "https://genshin-impact.fandom.com/wiki/Mona"
    },
    {
        "url": "https://genshin-impact.fandom.com/wiki/Ningguang"
    },
    {
        "url": "https://genshin-impact.fandom.com/wiki/Noelle"
    },
    {
        "url": "https://genshin-impact.fandom.com/wiki/Qiqi"
    },
    {
        "url": "https://genshin-impact.fandom.com/wiki/Raiden_Shogun"
    },
    {
        "url": "https://genshin-impact.fandom.com/wiki/Razor"
    },
    {
        "url": "https://genshin-impact.fandom.com/wiki/Rosaria"
    },
    {
        "url": "https://genshin-impact.fandom.com/wiki/Sangonomiya_Kokomi"
    },
    {
        "url": "https://genshin-impact.fandom.com/wiki/Sayu"
    },
    {
        "url": "https://genshin-impact.fandom.com/wiki/Shenhe"
    },
    {
        "url": "https://genshin-impact.fandom.com/wiki/Sucrose"
    },
    {
        "url": "https://genshin-impact.fandom.com/wiki/Tartaglia"
    },
    {
        "url": "https://genshin-impact.fandom.com/wiki/Thoma"
    },
    {
        "url": "https://genshin-impact.fandom.com/wiki/Traveler"
    },
    {
        "url": "https://genshin-impact.fandom.com/wiki/Venti"
    },
    {
        "url": "https://genshin-impact.fandom.com/wiki/Xiangling"
    },
    {
        "url": "https://genshin-impact.fandom.com/wiki/Xiao"
    },
    {
        "url": "https://genshin-impact.fandom.com/wiki/Xingqiu"
    },
    {
        "url": "https://genshin-impact.fandom.com/wiki/Xinyan"
    },
    {
        "url": "https://genshin-impact.fandom.com/wiki/Yanfei"
    },
    {
        "url": "https://genshin-impact.fandom.com/wiki/Yoimiya"
    },
    {
        "url": "https://genshin-impact.fandom.com/wiki/Yun_Jin"
    },
    {
        "url": "https://genshin-impact.fandom.com/wiki/Zhongli"
    }
]